litmus_libs/__init__.py
litmus_libs/models.py
litmus_libs/status_manager.py
litmus_libs/tls_reconciler.py
litmus_libs/utils.py
litmus_libs/interfaces/base.py
litmus_libs/interfaces/http_api.py
litmus_libs/interfaces/litmus_auth.py
litmus_libs/interfaces/self_monitoring.py
litmus_libs-0.0.10.dist-info/METADATA
litmus_libs-0.0.10.dist-info/WHEEL
litmus_libs-0.0.10.dist-info/licenses/LICENSE
litmus_libs-0.0.10.dist-info/RECORD
