Metadata-Version: 2.4
Name: litmus-libs
Version: 0.0.10
Summary: Shared abstractions for litmus component operator charms.
Project-URL: Homepage, https://github.com/canonical/litmus-operators
Project-URL: Bug Tracker, https://github.com/canonical/litmus-operators/issues
Author-email: mmkay <232859+mmkay@users.noreply.github.com>
License: 
License-File: LICENSE
Classifier: Development Status :: 4 - Beta
Classifier: Intended Audience :: Developers
Classifier: Intended Audience :: System Administrators
Classifier: License :: OSI Approved :: Apache Software License
Classifier: Operating System :: OS Independent
Classifier: Programming Language :: Python :: 3.12
Classifier: Topic :: Utilities
Classifier: Typing :: Typed
Requires-Python: <4,>=3.12
Requires-Dist: cosl
Requires-Dist: ops[tracing]>=3
Requires-Dist: pydantic
Provides-Extra: dev
Requires-Dist: coverage[toml]; extra == 'dev'
Requires-Dist: ops[testing]; extra == 'dev'
Requires-Dist: pyright; extra == 'dev'
Requires-Dist: pytest; extra == 'dev'
Requires-Dist: pytest-cov; extra == 'dev'
Requires-Dist: ruff; extra == 'dev'
